chefboost/Chefboost.py
chefboost/__init__.py
chefboost/commons/__init__.py
chefboost/commons/daemon.py
chefboost/commons/evaluate.py
chefboost/commons/functions.py
chefboost/commons/logger.py
chefboost/commons/module.py
chefboost/training/Preprocess.py
chefboost/training/Training.py
chefboost/training/__init__.py
chefboost/tuning/__init__.py
chefboost/tuning/adaboost.py
chefboost/tuning/gbm.py
chefboost/tuning/randomforest.py
PMSP_ml-0.1.dist-info/METADATA
PMSP_ml-0.1.dist-info/WHEEL
PMSP_ml-0.1.dist-info/top_level.txt
PMSP_ml-0.1.dist-info/RECORD
