Metadata-Version: 2.1
Name: PMSP-ml
Version: 0.1
Summary: Example Python package
Home-page: https://github.com/Dongguk-MAPS/PMSP_ml
Author: MAPS
Author-email: cjf4674@naver.com
License: MIT
Platform: UNKNOWN
Requires-Dist: docplex
Requires-Dist: pickle
Requires-Dist: numpy
